napari_open_ctc/__init__.py
napari_open_ctc/_reader.py
napari_open_ctc/_version.py
napari_open_ctc/napari.yaml
napari_open_ctc/reader.py
napari_open_ctc/_tests/__init__.py
napari_open_ctc/_tests/test_reader.py
napari_open_ctc/_tests/resources/TRA/README.md
napari_open_ctc/_tests/resources/TRA/man_track.txt
napari_open_ctc/_tests/resources/TRA/man_track000.tif
napari_open_ctc/_tests/resources/TRA/man_track001.tif
napari_open_ctc/_tests/resources/TRA/man_track002.tif
napari_open_ctc/_tests/resources/TRA/man_track003.tif
napari_open_ctc/_tests/resources/TRA/man_track004.tif
napari_open_ctc/_tests/resources/TRA/man_track005.tif
napari_open_ctc/_tests/resources/TRA/man_track006.tif
napari_open_ctc/_tests/resources/TRA/man_track007.tif
napari_open_ctc/_tests/resources/TRA/man_track008.tif
napari_open_ctc/_tests/resources/TRA/man_track009.tif
napari_open_ctc/_tests/resources/TRA/man_track010.tif
napari_open_ctc/_tests/resources/TRA/man_track011.tif
napari_open_ctc/_tests/resources/TRA/man_track012.tif
napari_open_ctc/_tests/resources/TRA/man_track013.tif
napari_open_ctc/_tests/resources/TRA/man_track014.tif
napari_open_ctc/_tests/resources/TRA/man_track015.tif
napari_open_ctc/_tests/resources/TRA/man_track016.tif
napari_open_ctc/_tests/resources/TRA/man_track017.tif
napari_open_ctc/_tests/resources/TRA/man_track018.tif
napari_open_ctc/_tests/resources/TRA/man_track019.tif
napari_open_ctc/_tests/resources/TRA/man_track020.tif
napari_open_ctc/_tests/resources/TRA/man_track021.tif
napari_open_ctc/_tests/resources/TRA/man_track022.tif
napari_open_ctc/_tests/resources/TRA/man_track023.tif
napari_open_ctc/_tests/resources/TRA/man_track024.tif
napari_open_ctc/_tests/resources/TRA/man_track025.tif
napari_open_ctc/_tests/resources/TRA/man_track026.tif
napari_open_ctc/_tests/resources/TRA/man_track027.tif
napari_open_ctc/_tests/resources/TRA/man_track028.tif
napari_open_ctc/_tests/resources/TRA/man_track029.tif
napari_open_ctc/_tests/resources/TRA/man_track030.tif
napari_open_ctc-0.1.2.dist-info/LICENSE
napari_open_ctc-0.1.2.dist-info/METADATA
napari_open_ctc-0.1.2.dist-info/WHEEL
napari_open_ctc-0.1.2.dist-info/entry_points.txt
napari_open_ctc-0.1.2.dist-info/top_level.txt
napari_open_ctc-0.1.2.dist-info/RECORD
