Metadata-Version: 2.1
Name: napari-open-ctc
Version: 0.1.2
Summary: "Drag and drop annotations/results in the Cell Tracking Challenge (CTC) format into napari."
Home-page: https://github.com/bentaculum/napari-open-ctc
Author: Benjamin Gallusser
Author-email: benjamin.gallusser@epfl.ch
License: BSD-3-Clause
Project-URL: Bug Tracker, https://github.com/bentaculum/napari-open-ctc/issues
Project-URL: Documentation, https://github.com/bentaculum/napari-open-ctc#README.md
Project-URL: Source Code, https://github.com/bentaculum/napari-open-ctc
Project-URL: User Support, https://github.com/bentaculum/napari-open-ctc/issues
Classifier: Development Status :: 3 - Alpha
Classifier: Framework :: napari
Classifier: License :: OSI Approved :: BSD License
Classifier: Operating System :: OS Independent
Classifier: Programming Language :: Python
Classifier: Programming Language :: Python :: 3
Classifier: Programming Language :: Python :: 3 :: Only
Classifier: Programming Language :: Python :: 3.9
Classifier: Programming Language :: Python :: 3.10
Classifier: Programming Language :: Python :: 3.11
Classifier: Topic :: Scientific/Engineering :: Image Processing
Requires-Python: >=3.9
License-File: LICENSE
Requires-Dist: napari
Requires-Dist: numpy
Requires-Dist: scikit-image
Requires-Dist: tifffile
Requires-Dist: pandas
Requires-Dist: imagecodecs
Provides-Extra: testing
Requires-Dist: tox ; extra == 'testing'
Requires-Dist: pytest ; extra == 'testing'
Requires-Dist: pytest-cov ; extra == 'testing'
